{
  "prospects": {},
  "profiles": {
    "demo-user": {
      "id": "demo-user",
      "submarkets": [
        "Nisku",
        "Leduc"
      ],
      "updatedAt": "2025-09-21T18:25:46.383Z"
    },
    "demo-user-2": {
      "id": "demo-user-2",
      "name": "Teammate Two"
    },
    "a8ea73b9-cf94-45cc-a556-cfbf036da8a4": {
      "id": "a8ea73b9-cf94-45cc-a556-cfbf036da8a4",
      "submarkets": [
        "nisku"
      ],
      "updatedAt": "2025-09-23T20:33:25.284Z"
    }
  },
  "interactions": {},
  "requirements": {
    "demo-user": [
      {
        "id": "f6f4f0a5-06bf-4232-9237-ba1a18db58d4",
        "userId": "demo-user",
        "title": "asdasd",
        "source": "Avison",
        "location": "Leduc",
        "contactName": "",
        "contactEmail": "",
        "contactPhone": "",
        "spaceSize": "5,000 - 10,000 SF",
        "timeline": null,
        "status": "active",
        "tags": [],
        "notes": "asdsa",
        "createdAt": "2025-09-22T17:06:46.543Z",
        "updatedAt": "2025-09-22T17:06:46.543Z"
      },
      {
        "id": "7aa745ca-c893-48fa-92db-774c76a87528",
        "userId": "demo-user",
        "title": "rebel",
        "source": null,
        "location": "b",
        "contactName": "",
        "contactEmail": "",
        "contactPhone": "",
        "spaceSize": "10,000 - 25,000 SF",
        "timeline": null,
        "status": "fulfilled",
        "tags": [],
        "notes": "",
        "createdAt": "2025-09-22T17:09:48.722Z",
        "updatedAt": "2025-09-22T17:09:48.722Z"
      },
      {
        "id": "574d8898-9820-4f48-9469-b1cba5184148",
        "userId": "demo-user",
        "title": "asdada",
        "source": "Avison",
        "location": "",
        "contactName": "",
        "contactEmail": "",
        "contactPhone": "",
        "spaceSize": null,
        "timeline": null,
        "status": "active",
        "tags": [],
        "notes": "",
        "createdAt": "2025-09-30T19:07:10.145Z",
        "updatedAt": "2025-09-30T19:07:10.145Z"
      },
      {
        "id": "4f7bcbed-f17e-49c8-9d12-1e141cf54b96",
        "userId": "demo-user",
        "title": "ZXC",
        "source": "Avison",
        "location": "b",
        "contactName": "ZX",
        "contactEmail": "",
        "contactPhone": "",
        "spaceSize": null,
        "timeline": null,
        "status": "active",
        "tags": [],
        "notes": "",
        "createdAt": "2025-11-11T21:34:25.265Z",
        "updatedAt": "2025-11-11T21:34:25.265Z"
      }
    ],
    "demo-user-2": [
      {
        "id": "demo-user-2-r1",
        "title": "Tenant need 5k sf",
        "createdAt": "2025-09-18T17:20:14.745Z"
      },
      {
        "id": "demo-user-2-r2",
        "title": "Buyer search 2 acres",
        "createdAt": "2025-09-21T17:20:14.745Z"
      }
    ],
    "a8ea73b9-cf94-45cc-a556-cfbf036da8a4": [
      {
        "id": "7937e548-fc2e-4a82-922d-f9dc3990eed3",
        "userId": "a8ea73b9-cf94-45cc-a556-cfbf036da8a4",
        "title": "1231",
        "source": "JLL",
        "location": "",
        "contactName": "",
        "contactEmail": "",
        "contactPhone": "",
        "spaceSize": "5,000 - 10,000 SF",
        "timeline": null,
        "status": "expired",
        "tags": [],
        "notes": "",
        "createdAt": "2025-09-23T20:33:20.226Z",
        "updatedAt": "2025-09-23T20:33:20.226Z"
      }
    ]
  },
  "submarkets": {
    "demo-user": [
      {
        "id": "170f277d-8e61-4e1f-99c1-3b8a6ffccc6f",
        "userId": "demo-user",
        "name": "a",
        "color": "#41b",
        "isActive": true,
        "createdAt": "2025-09-21T05:47:46.715Z",
        "updatedAt": "2025-09-21T05:47:46.715Z"
      },
      {
        "id": "d1120d10-206f-46c0-8cdc-496ffc301102",
        "userId": "demo-user",
        "name": "a",
        "color": "#1b71a4",
        "isActive": true,
        "createdAt": "2025-09-21T05:47:49.093Z",
        "updatedAt": "2025-09-21T05:47:49.093Z"
      },
      {
        "id": "ba808e10-4c18-42f3-825c-9c05e03fa0c8",
        "userId": "demo-user",
        "name": "s",
        "color": "#b94aca",
        "isActive": true,
        "createdAt": "2025-09-21T05:47:49.194Z",
        "updatedAt": "2025-09-21T05:47:49.194Z"
      },
      {
        "id": "e9b3fe3c-ab53-4149-b330-0bf1755f7074",
        "userId": "demo-user",
        "name": "a",
        "color": "#4b8843",
        "isActive": true,
        "createdAt": "2025-09-21T05:47:51.552Z",
        "updatedAt": "2025-09-21T05:47:51.552Z"
      },
      {
        "id": "49eea947-e219-4221-9b5b-5233e2d197ef",
        "userId": "demo-user",
        "name": "s",
        "color": "#b43983",
        "isActive": true,
        "createdAt": "2025-09-21T05:47:51.664Z",
        "updatedAt": "2025-09-21T05:47:51.664Z"
      },
      {
        "id": "3dc0cea4-a568-4b1d-8e16-05d96046d570",
        "userId": "demo-user",
        "name": "b",
        "color": "#83012a",
        "isActive": true,
        "createdAt": "2025-09-21T05:47:51.773Z",
        "updatedAt": "2025-09-21T05:47:51.773Z"
      },
      {
        "id": "fc718e48-bfe1-41e5-b9e9-4b0cdaafe68a",
        "userId": "demo-user",
        "name": "a",
        "color": "#63717c",
        "isActive": true,
        "createdAt": "2025-09-21T18:25:36.341Z",
        "updatedAt": "2025-09-21T18:25:36.341Z"
      },
      {
        "id": "66f089b5-40cd-4c03-ac03-e866a30e43c9",
        "userId": "demo-user",
        "name": "s",
        "color": "#fac373",
        "isActive": true,
        "createdAt": "2025-09-21T18:25:36.438Z",
        "updatedAt": "2025-09-21T18:25:36.438Z"
      },
      {
        "id": "73b30bf7-ee00-4383-a7d7-ad913b4001a5",
        "userId": "demo-user",
        "name": "a",
        "color": "#b3b403",
        "isActive": true,
        "createdAt": "2025-09-21T18:25:38.474Z",
        "updatedAt": "2025-09-21T18:25:38.474Z"
      },
      {
        "id": "b8f6f960-5db4-440b-9069-627f0c886ba9",
        "userId": "demo-user",
        "name": "s",
        "color": "#c27896",
        "isActive": true,
        "createdAt": "2025-09-21T18:25:38.569Z",
        "updatedAt": "2025-09-21T18:25:38.569Z"
      },
      {
        "id": "f216855c-a906-4d1f-8a74-544423fac573",
        "userId": "demo-user",
        "name": "Nisku",
        "color": "#71e45d",
        "isActive": true,
        "createdAt": "2025-09-21T18:25:38.664Z",
        "updatedAt": "2025-09-21T18:25:38.664Z"
      },
      {
        "id": "79dcd41b-20b9-4c71-bd04-f18ff9d6b7cc",
        "userId": "demo-user",
        "name": "a",
        "color": "#9ace5b",
        "isActive": true,
        "createdAt": "2025-09-21T18:25:42.331Z",
        "updatedAt": "2025-09-21T18:25:42.331Z"
      },
      {
        "id": "9ec1e287-82f3-47aa-8af3-d9cac717b71a",
        "userId": "demo-user",
        "name": "Nisku",
        "color": "#70157c",
        "isActive": true,
        "createdAt": "2025-09-21T18:25:42.444Z",
        "updatedAt": "2025-09-21T18:25:42.444Z"
      },
      {
        "id": "0d1cc95a-f846-4ac3-bf2d-e1b255b8f8cd",
        "userId": "demo-user",
        "name": "Nisku",
        "color": "#bd71b7",
        "isActive": true,
        "createdAt": "2025-09-21T18:25:42.929Z",
        "updatedAt": "2025-09-21T18:25:42.929Z"
      },
      {
        "id": "f5171fc6-c1d1-4cb0-af4f-68e0bb5d95ae",
        "userId": "demo-user",
        "name": "Nisku",
        "color": "#77d772",
        "isActive": true,
        "createdAt": "2025-09-21T18:25:46.220Z",
        "updatedAt": "2025-09-21T18:25:46.220Z"
      },
      {
        "id": "9fe0d7e2-ec10-4c07-80df-8b101afb4c04",
        "userId": "demo-user",
        "name": "Leduc",
        "color": "#401518",
        "isActive": true,
        "createdAt": "2025-09-21T18:25:46.318Z",
        "updatedAt": "2025-09-21T18:25:46.318Z"
      }
    ],
    "a8ea73b9-cf94-45cc-a556-cfbf036da8a4": [
      {
        "id": "425ae8c4-093f-45e1-b8c0-bd423dbd3b50",
        "userId": "a8ea73b9-cf94-45cc-a556-cfbf036da8a4",
        "name": "nisku",
        "color": "#c31bbe",
        "isActive": true,
        "createdAt": "2025-09-23T20:33:25.237Z",
        "updatedAt": "2025-09-23T20:33:25.237Z"
      }
    ]
  },
  "marketComps": {
    "demo-user": [
      {
        "id": "c40964f2-c9a3-452d-b1f7-0f7b435375d4",
        "userId": "demo-user",
        "address": "1234",
        "submarket": "a",
        "assetType": "Land",
        "buildingSize": null,
        "landSize": null,
        "sourceLink": null,
        "notes": null,
        "dealType": "lease",
        "tenant": null,
        "termMonths": 5,
        "rate": null,
        "rateType": "Net",
        "commencement": "2025-09-02",
        "concessions": null,
        "saleDate": null,
        "buyer": null,
        "seller": null,
        "price": null,
        "pricePerSf": null,
        "pricePerAcre": null,
        "createdAt": "2025-09-21T19:52:13.188Z",
        "updatedAt": "2025-09-21T19:52:13.188Z"
      },
      {
        "id": "8aea6f7d-8100-4958-99f2-36a1778e464f",
        "userId": "demo-user",
        "address": "123123",
        "submarket": null,
        "assetType": "Building",
        "buildingSize": null,
        "landSize": null,
        "sourceLink": null,
        "notes": null,
        "dealType": "lease",
        "tenant": null,
        "termMonths": 72,
        "rate": "11.5",
        "rateType": null,
        "commencement": null,
        "concessions": null,
        "saleDate": "2025-09-03",
        "buyer": null,
        "seller": null,
        "price": "900000",
        "pricePerSf": null,
        "pricePerAcre": null,
        "createdAt": "2025-09-21T19:55:57.438Z",
        "updatedAt": "2025-09-21T20:16:21.183Z"
      },
      {
        "id": "f74f4e2b-d171-46c4-a64b-93a912397c0d",
        "userId": "demo-user",
        "address": "12412313",
        "submarket": null,
        "assetType": "Building",
        "buildingSize": null,
        "landSize": null,
        "sourceLink": null,
        "notes": null,
        "dealType": "lease",
        "tenant": null,
        "termMonths": null,
        "rate": "9.50",
        "rateType": null,
        "commencement": null,
        "concessions": null,
        "saleDate": "2025-09-24",
        "buyer": null,
        "seller": null,
        "price": null,
        "pricePerSf": null,
        "pricePerAcre": null,
        "createdAt": "2025-09-21T19:56:02.480Z",
        "updatedAt": "2025-09-21T20:08:09.798Z"
      },
      {
        "id": "941a8710-e08b-45cc-8ea9-717da4cdd2cf",
        "userId": "demo-user",
        "address": "234234",
        "submarket": null,
        "assetType": "Building",
        "buildingSize": null,
        "landSize": null,
        "sourceLink": null,
        "notes": null,
        "dealType": "sale",
        "tenant": null,
        "termMonths": null,
        "rate": null,
        "rateType": null,
        "commencement": null,
        "concessions": null,
        "saleDate": null,
        "buyer": null,
        "seller": null,
        "price": null,
        "pricePerSf": null,
        "pricePerAcre": null,
        "createdAt": "2025-09-21T19:57:02.433Z",
        "updatedAt": "2025-09-21T19:57:02.433Z"
      }
    ],
    "demo-user-2": [
      {
        "id": "demo-user-2-c1",
        "address": "123 Main St",
        "createdAt": "2025-09-17T17:20:14.745Z"
      }
    ],
    "a8ea73b9-cf94-45cc-a556-cfbf036da8a4": [
      {
        "id": "bbd4ed18-eded-4d81-90b5-49e77817a535",
        "userId": "a8ea73b9-cf94-45cc-a556-cfbf036da8a4",
        "address": "123",
        "submarket": null,
        "assetType": "Building",
        "buildingSize": null,
        "landSize": null,
        "sourceLink": null,
        "notes": null,
        "dealType": "lease",
        "tenant": null,
        "termMonths": null,
        "rate": "10.00",
        "rateType": null,
        "commencement": "2025-09-04",
        "concessions": null,
        "saleDate": null,
        "buyer": null,
        "seller": null,
        "price": null,
        "pricePerSf": null,
        "pricePerAcre": null,
        "createdAt": "2025-09-23T20:33:06.734Z",
        "updatedAt": "2025-09-23T20:33:06.734Z"
      }
    ]
  },
  "listings": {
    "demo-user": [
      {
        "id": "682523dd-90c0-47f5-afc9-ff419d7b2d43",
        "userId": "demo-user",
        "title": "nw",
        "address": "nw",
        "lat": "",
        "lng": "",
        "submarket": null,
        "createdAt": "2025-09-22T13:24:43.488Z",
        "archivedAt": "2025-09-22T16:03:59.830Z"
      },
      {
        "id": "5e89732d-6ed3-4bc0-9951-51a4f530362e",
        "userId": "demo-user",
        "title": "test",
        "address": "test",
        "lat": "",
        "lng": "",
        "submarket": null,
        "createdAt": "2025-09-22T13:25:46.473Z",
        "archivedAt": "2025-09-22T16:02:56.356Z"
      },
      {
        "id": "e98b3aac-6b26-4407-a02b-c80f22e68487",
        "userId": "demo-user",
        "title": "465",
        "address": "465",
        "lat": "",
        "lng": "",
        "submarket": null,
        "createdAt": "2025-09-22T13:27:44.067Z",
        "archivedAt": "2025-09-22T16:01:09.206Z"
      },
      {
        "id": "7726c688-c17c-436b-891a-c2b3aef24a0a",
        "userId": "demo-user",
        "title": "456564",
        "address": "456564",
        "lat": "",
        "lng": "",
        "submarket": null,
        "createdAt": "2025-09-22T13:32:39.925Z",
        "archivedAt": "2025-09-22T16:01:08.344Z"
      },
      {
        "id": "01115cc7-679c-4eee-a3a3-bafae73d9cd8",
        "userId": "demo-user",
        "title": "sad",
        "address": "sad",
        "lat": "",
        "lng": "",
        "submarket": null,
        "createdAt": "2025-09-22T13:40:30.477Z",
        "archivedAt": "2025-09-22T16:01:07.779Z"
      },
      {
        "id": "319f720e-3f0b-4f5d-9e1b-dd80124a8c2b",
        "userId": "demo-user",
        "title": "asd",
        "address": "asd",
        "lat": "",
        "lng": "",
        "submarket": null,
        "createdAt": "2025-09-22T14:29:43.410Z",
        "archivedAt": "2025-09-22T16:01:07.245Z"
      },
      {
        "id": "b2d5385c-ca46-41e3-a712-9b2b7a28191c",
        "userId": "demo-user",
        "title": "a",
        "address": "a",
        "lat": "",
        "lng": "",
        "submarket": null,
        "createdAt": "2025-09-22T14:59:46.787Z",
        "archivedAt": "2025-09-22T16:01:06.284Z"
      },
      {
        "id": "73b70829-2d37-4fd7-aae2-c1553d6766a9",
        "userId": "demo-user",
        "title": "test",
        "address": "test",
        "lat": "",
        "lng": "",
        "submarket": null,
        "createdAt": "2025-09-22T16:07:44.507Z",
        "archivedAt": "2025-09-22T16:26:17.641Z"
      },
      {
        "id": "b1091d91-f94f-4189-8e9e-c7ecfd68bd40",
        "userId": "demo-user",
        "title": "sdasd",
        "address": "sdasd",
        "lat": "",
        "lng": "",
        "submarket": null,
        "createdAt": "2025-09-23T16:06:25.993Z",
        "archivedAt": null
      },
      {
        "id": "87eba8c8-cd70-489e-947c-ebcb76d2eff9",
        "userId": "demo-user",
        "title": "test 12312",
        "address": "test 12312",
        "lat": "",
        "lng": "",
        "submarket": null,
        "createdAt": "2025-09-23T18:21:10.807Z",
        "archivedAt": null
      },
      {
        "id": "d63c864f-fc0c-49d7-ac56-929e5ea10bdb",
        "userId": "demo-user",
        "title": "teswt",
        "address": "teswt",
        "lat": "",
        "lng": "",
        "submarket": null,
        "createdAt": "2025-09-26T16:47:39.400Z",
        "archivedAt": null
      }
    ],
    "a8ea73b9-cf94-45cc-a556-cfbf036da8a4": [
      {
        "id": "b63a2007-cf55-492f-be9d-717400e74276",
        "userId": "a8ea73b9-cf94-45cc-a556-cfbf036da8a4",
        "title": "tes",
        "address": "tes",
        "lat": "",
        "lng": "",
        "submarket": null,
        "createdAt": "2025-09-23T18:07:57.049Z",
        "archivedAt": null
      },
      {
        "id": "6f9dd7a3-2ec8-4728-ae69-2fce607be4f1",
        "userId": "a8ea73b9-cf94-45cc-a556-cfbf036da8a4",
        "title": "tesss",
        "address": "tesss",
        "lat": "",
        "lng": "",
        "submarket": null,
        "createdAt": "2025-09-23T18:08:06.536Z",
        "archivedAt": null
      },
      {
        "id": "48237e3e-4248-4047-8d95-ae625e5a7e62",
        "userId": "a8ea73b9-cf94-45cc-a556-cfbf036da8a4",
        "title": "FOGT",
        "address": "FOGT",
        "lat": "",
        "lng": "",
        "submarket": null,
        "createdAt": "2025-09-23T18:47:34.939Z",
        "archivedAt": null
      },
      {
        "id": "3ea7a74d-05b3-4299-a9da-0825c8af2a57",
        "userId": "a8ea73b9-cf94-45cc-a556-cfbf036da8a4",
        "title": "TEst12 123",
        "address": "TEst12 123",
        "lat": "",
        "lng": "",
        "submarket": null,
        "createdAt": "2025-09-23T20:04:41.759Z",
        "archivedAt": null
      },
      {
        "id": "346ddac1-6918-487e-9541-96838c817d07",
        "userId": "a8ea73b9-cf94-45cc-a556-cfbf036da8a4",
        "title": "test",
        "address": "test",
        "lat": "",
        "lng": "",
        "submarket": null,
        "createdAt": "2025-09-23T20:28:51.158Z",
        "archivedAt": null
      },
      {
        "id": "11199b0e-b495-4b52-8627-465fd5b73f11",
        "userId": "a8ea73b9-cf94-45cc-a556-cfbf036da8a4",
        "title": "sdasddadadas S",
        "address": "sdasddadadas S",
        "lat": "",
        "lng": "",
        "submarket": null,
        "createdAt": "2025-09-23T20:29:19.421Z",
        "archivedAt": null
      }
    ]
  },
  "listingLinks": {}
}
